bidsphysio.session-21.6.24-py3.8-nspkg.pth
bidsphysio/session/__init__.py
bidsphysio/session/info.py
bidsphysio/session/session2bids.py
tests/__init__.py
tests/test_session2bids.py
tests/utils.py
bidsphysio.session-21.6.24.dist-info/METADATA
bidsphysio.session-21.6.24.dist-info/WHEEL
bidsphysio.session-21.6.24.dist-info/namespace_packages.txt
bidsphysio.session-21.6.24.dist-info/top_level.txt
bidsphysio.session-21.6.24.dist-info/RECORD
